LICENSE
MANIFEST.in
README.rst
setup.py
seacucumber/__init__.py
seacucumber/backend.py
seacucumber/models.py
seacucumber/tasks.py
seacucumber/util.py
seacucumber.egg-info/PKG-INFO
seacucumber.egg-info/SOURCES.txt
seacucumber.egg-info/dependency_links.txt
seacucumber.egg-info/requires.txt
seacucumber.egg-info/top_level.txt
seacucumber/management/__init__.py
seacucumber/management/commands/__init__.py
seacucumber/management/commands/ses_address.py
seacucumber/management/commands/ses_usage.py