Metadata-Version: 1.1
Name: seacucumber
Version: 1.5.1
Summary: A Django email backend for Amazon Simple Email Service, backed by celery.
Home-page: https://github.com/duointeractive/sea-cucumber/
Author: Gregory Taylor
Author-email: gtaylor@duointeractive.com
License: MIT
Platform: any
Classifier: Development Status :: 5 - Production/Stable
Classifier: Intended Audience :: Developers
Classifier: License :: OSI Approved :: MIT License
Classifier: Operating System :: OS Independent
Classifier: Programming Language :: Python
Classifier: Topic :: Software Development :: Libraries :: Python Modules
Classifier: Framework :: Django
